hatch_module_yorailevi/__about__.py
hatch_module_yorailevi/__init__.py
hatch_module_yorailevi-0.0.7.dist-info/METADATA
hatch_module_yorailevi-0.0.7.dist-info/WHEEL
hatch_module_yorailevi-0.0.7.dist-info/licenses/LICENSE.txt
hatch_module_yorailevi-0.0.7.dist-info/RECORD
