Metadata-Version: 2.3
Name: hatch-module-yorailevi
Version: 0.0.7
Project-URL: Documentation, https://github.com/YoraiLevi/pip_installable_module#readme
Project-URL: Issues, https://github.com/YoraiLevi/pip_installable_module/issues
Project-URL: Source, https://github.com/YoraiLevi/pip_installable_module
Author-email: Yorai Levi <yorai.email@gmail.com>
License-Expression: MIT
License-File: LICENSE.txt
Classifier: Development Status :: 4 - Beta
Classifier: Programming Language :: Python
Classifier: Programming Language :: Python :: 3.8
Classifier: Programming Language :: Python :: 3.9
Classifier: Programming Language :: Python :: 3.10
Classifier: Programming Language :: Python :: 3.11
Classifier: Programming Language :: Python :: 3.12
Classifier: Programming Language :: Python :: Implementation :: CPython
Classifier: Programming Language :: Python :: Implementation :: PyPy
Requires-Python: >=3.8
